COPYING
MANIFEST.in
README.md
requirements.txt
setup.cfg
setup.py
cleaninsights/__init__.py
cleaninsights/aggregation_period.py
cleaninsights/aggregation_rule.py
cleaninsights/campaign.py
cleaninsights/conf.py
cleaninsights/datapoint.py
cleaninsights/event.py
cleaninsights/visit.py
cleaninsights.egg-info/PKG-INFO
cleaninsights.egg-info/SOURCES.txt
cleaninsights.egg-info/dependency_links.txt
cleaninsights.egg-info/requires.txt
cleaninsights.egg-info/top_level.txt
cleaninsights/store/__init__.py
cleaninsights/store/memory.py